bcrnnoise.py
bcrnnoise-3.0.4.dist-info/METADATA
bcrnnoise-3.0.4.dist-info/WHEEL
bcrnnoise-3.0.4.dist-info/licenses/LICENSE
bcrnnoise-3.0.4.dist-info/RECORD
