Metadata-Version: 2.4
Name: bcrnnoise
Version: 3.0.4
Project-URL: Repository, https://github.com/BioDisCo/bcrnnoise.git
Author-email: Arman Ferdowsi <ferdowsi@ecs.tuwien.ac.at>, Matthias Függer <mfuegger@lmf.cnrs.fr>, Thomas Nowak <thomas@thomasnowak.net>
Maintainer-email: Arman Ferdowsi <ferdowsi@ecs.tuwien.ac.at>, Matthias Függer <mfuegger@lmf.cnrs.fr>, Thomas Nowak <thomas@thomasnowak.net>
License:                                  Apache License
License-File: LICENSE
Classifier: Programming Language :: Python
Requires-Python: >=3.11
Requires-Dist: matplotlib
Requires-Dist: numpy
Requires-Dist: pint
Requires-Dist: solve-ivp-pint~=1.0.0
